pgql/__init__.py
pgql/graphql/__init__.py
pgql/graphql/executor.py
pgql/graphql/utils.py
pgql/graphql/directives/__init__.py
pgql/graphql/directives/base.py
pgql/graphql/errors/__init__.py
pgql/graphql/errors/definition_error.py
pgql/graphql/resolvers/__init__.py
pgql/graphql/resolvers/base.py
pgql/http/authorize_info.py
pgql/http/config.py
pgql/http/config_http_enum.py
pgql/http/http.py
pgql/http/session.py
pgql-0.5.8.dist-info/METADATA
pgql-0.5.8.dist-info/WHEEL
pgql-0.5.8.dist-info/top_level.txt
pgql-0.5.8.dist-info/RECORD
