Metadata-Version: 2.4
Name: pgql
Version: 0.5.8
Summary: A lightweight Python GraphQL server framework with automatic resolver mapping and schema introspection
Author-email: Pablo Muñoz <pjmd89@gmail.com>
License: MIT
Project-URL: Homepage, https://github.com/pjmd89/pygql
Project-URL: Repository, https://github.com/pjmd89/pygql
Project-URL: Documentation, https://github.com/pjmd89/pygql#readme
Project-URL: Issues, https://github.com/pjmd89/pygql/issues
Keywords: graphql,api,server,starlette,uvicorn,schema,resolver
Classifier: Development Status :: 4 - Beta
Classifier: Intended Audience :: Developers
Classifier: License :: OSI Approved :: MIT License
Classifier: Programming Language :: Python :: 3
Classifier: Programming Language :: Python :: 3.8
Classifier: Programming Language :: Python :: 3.9
Classifier: Programming Language :: Python :: 3.10
Classifier: Programming Language :: Python :: 3.11
Classifier: Programming Language :: Python :: 3.12
Classifier: Programming Language :: Python :: 3.13
Classifier: Topic :: Internet :: WWW/HTTP :: HTTP Servers
Classifier: Topic :: Software Development :: Libraries :: Application Frameworks
Classifier: Framework :: AsyncIO
Requires-Python: >=3.8
Requires-Dist: graphql-core>=3.2.0
Requires-Dist: starlette>=0.27.0
Requires-Dist: uvicorn[standard]>=0.23.0
Requires-Dist: pyyaml>=6.0
Provides-Extra: dev
Requires-Dist: pytest>=7.0; extra == "dev"
Requires-Dist: black>=22.0; extra == "dev"
Requires-Dist: flake8>=4.0; extra == "dev"
